improved_datamodel_codegen/__init__.py
improved_datamodel_codegen/__main__.py
improved_datamodel_codegen/format.py
improved_datamodel_codegen/http.py
improved_datamodel_codegen/imports.py
improved_datamodel_codegen/model/__init__.py
improved_datamodel_codegen/model/base.py
improved_datamodel_codegen/model/enum.py
improved_datamodel_codegen/model/pydantic/__init__.py
improved_datamodel_codegen/model/pydantic/base_model.py
improved_datamodel_codegen/model/pydantic/custom_root_type.py
improved_datamodel_codegen/model/pydantic/dataclass.py
improved_datamodel_codegen/model/pydantic/imports.py
improved_datamodel_codegen/model/pydantic/types.py
improved_datamodel_codegen/model/template/Enum.jinja2
improved_datamodel_codegen/model/template/dataclass.jinja2
improved_datamodel_codegen/model/template/pydantic/BaseModel.jinja2
improved_datamodel_codegen/model/template/pydantic/BaseModel_root.jinja2
improved_datamodel_codegen/model/template/pydantic/Config.jinja2
improved_datamodel_codegen/model/template/pydantic/dataclass.jinja2
improved_datamodel_codegen/parser/__init__.py
improved_datamodel_codegen/parser/base.py
improved_datamodel_codegen/parser/jsonschema.py
improved_datamodel_codegen/parser/openapi.py
improved_datamodel_codegen/reference.py
improved_datamodel_codegen/types.py
improved_datamodel_codegen/version.py
improved_datamodel_codegen-1.2.1.dist-info/LICENSE
improved_datamodel_codegen-1.2.1.dist-info/WHEEL
improved_datamodel_codegen-1.2.1.dist-info/entry_points.txt
improved_datamodel_codegen-1.2.1.dist-info/METADATA
improved_datamodel_codegen-1.2.1.dist-info/RECORD
